argmagiq/__init__.py
argmagiq/config_spec.py
argmagiq/decorators.py
argmagiq/magiq_parser.py
argmagiq/value_spec.py
argmagiq/parsers/__init__.py
argmagiq/parsers/bool_parser.py
argmagiq/parsers/data_type_parser.py
argmagiq/parsers/float_parser.py
argmagiq/parsers/int_parser.py
argmagiq/parsers/str_parser.py
argmagiq-0.1.0.data/data/LICENSE
argmagiq-0.1.0.data/data/README.md
argmagiq-0.1.0.dist-info/LICENSE
argmagiq-0.1.0.dist-info/METADATA
argmagiq-0.1.0.dist-info/WHEEL
argmagiq-0.1.0.dist-info/top_level.txt
argmagiq-0.1.0.dist-info/RECORD
