Metadata-Version: 2.1
Name: argmagiq
Version: 0.1.0
Summary: A Python library for parsing command-line args automagically.
Home-page: https://github.com/phohenecker/arg-magiq
Author: Patrick Hohenecker
Author-email: mail@paho.at
License: BSD-2-Clause
Platform: UNKNOWN
Classifier: Programming Language :: Python :: 3.7
Classifier: Programming Language :: Python :: 3.8
Requires-Python: >=3.7
Requires-Dist: insanity (>=2017.1)
